sue/defaults.py
sue/admin.py
sue/__init__.py
sue/models.py
sue/page_processors.py
sue/views.py
sue/tests.py
sue/migrations/__init__.py
sue/templates/base.html~
sue/templates/base.html
sue/templates/pages/portfolio.html
sue/templates/pages/portfolios.html
sue/templates/pages/portfolioitem.html~
sue/templates/pages/tempportfolio.html
sue/templates/pages/portfolio.html~
sue/templates/pages/index.html~
sue/templates/pages/portfolios.html~
sue/templates/pages/portfolioitem.html
sue/templates/pages/index.html
sue/templates/pages/tempportfolio.html~
sue/templates/pages/homepage.html
sue/templates/pages/documentlist.html
sue/templates/pages/menus/dropdown.html
sue/templates/pages/menus/tree.html
sue/templates/pages/menus/dropdown.html~
sue/templates/pages/menus/tree.html~
sue/static/fonts/glyphicons-halflings-regular.eot
sue/static/fonts/glyphicons-halflings-regular.woff
sue/static/fonts/glyphicons-halflings-regular.ttf
sue/static/fonts/glyphicons-halflings-regular.woff2
sue/static/fonts/glyphicons-halflings-regular.svg
sue/static/js/application.js
sue/static/js/jquery.jcarousel.js
sue/static/js/bootstrap.min.js
sue/static/js/carousel.js~
sue/static/js/jquery.js
sue/static/js/jquery.tweet.js
sue/static/js/camera.js
sue/static/js/jquery.easing.1.3.js
sue/static/js/jquery.mobile.customized.min.js
sue/static/js/carousel.js
sue/static/js/jquery.prettyPhoto.js
sue/static/js/myscript.js
sue/static/js/npm.js
sue/static/js/bootstrap.js
sue/static/js/jquery.preloader.js
sue/static/js/superfish.js
sue/static/js/sorting.js
sue/static/js/jquery.isotope.min.js
sue/static/js/google-code-prettify/prettify.css
sue/static/js/google-code-prettify/prettify.js
sue/static/img/slider_nav.png
sue/static/img/line.png
sue/static/img/3.jpg
sue/static/img/long_wall.jpeg
sue/static/img/Bushmans.jpg
sue/static/img/django.gif
sue/static/css/bootstrap-responsive.css
sue/static/css/bootstrap_flatly.css
sue/static/css/bootstrap-theme.min.css
mezzanine_sue-0.2.6.dist-info/RECORD
mezzanine_sue-0.2.6.dist-info/WHEEL
mezzanine_sue-0.2.6.dist-info/METADATA
mezzanine_sue-0.2.6.dist-info/top_level.txt
mezzanine_sue-0.2.6.dist-info/DESCRIPTION.rst
mezzanine_sue-0.2.6.dist-info/metadata.json
